pyvacy/__init__.py
pyvacy/analysis/__init__.py
pyvacy/analysis/analytical_moments_accountant.py
pyvacy/analysis/moments_accountant.py
pyvacy/analysis/rdp_accountant.py
pyvacy/optim/__init__.py
pyvacy/optim/dp_optimizer.py
pyvacy-0.0.31.dist-info/LICENSE
pyvacy-0.0.31.dist-info/METADATA
pyvacy-0.0.31.dist-info/WHEEL
pyvacy-0.0.31.dist-info/top_level.txt
pyvacy-0.0.31.dist-info/RECORD
