Metadata-Version: 2.1
Name: pyvacy
Version: 0.0.31
Summary: Privacy preserving deep learning for PyTorch
Home-page: http://github.com/ChrisWaites/pyvacy
Author: Chris Waites
Author-email: cwaites10@gmail.com
License: UNKNOWN
Platform: UNKNOWN
